KDEpy/binning.py
KDEpy/kernel_funcs.py
KDEpy/__init__.py
KDEpy/_cutils.cpython-312-darwin.so
KDEpy/FFTKDE.py
KDEpy/TreeKDE.py
KDEpy/NaiveKDE.py
KDEpy/BaseKDE.py
KDEpy/bw_selection.py
KDEpy/utils.py
KDEpy/cutils_ext/cutils.c
KDEpy/cutils_ext/cutils.pyx
kdepy-1.1.12.dist-info/RECORD
kdepy-1.1.12.dist-info/WHEEL
kdepy-1.1.12.dist-info/top_level.txt
kdepy-1.1.12.dist-info/METADATA
kdepy-1.1.12.dist-info/licenses/LICENSE
