Metadata-Version: 2.4
Name: KDEpy
Version: 1.1.12
Summary: Kernel Density Estimation in Python.
Author-email: tommyod <tommy.odland@gmail.com>
License: BSD 3-Clause License
Project-URL: Repository, https://github.com/tommyod/KDEpy
Classifier: Development Status :: 5 - Production/Stable
Classifier: License :: OSI Approved :: BSD License
Classifier: Programming Language :: Python :: 3.8
Classifier: Programming Language :: Python :: 3.9
Classifier: Programming Language :: Python :: 3.10
Classifier: Programming Language :: Python :: 3.11
Classifier: Programming Language :: Python :: 3.12
Classifier: Programming Language :: Python :: 3.13
License-File: LICENSE
Requires-Dist: numpy>=1.14.2
Requires-Dist: scipy<2.0,>=1.0.1
Provides-Extra: dev
Requires-Dist: sphinx<7; extra == "dev"
Requires-Dist: numpydoc>=0.7.0; extra == "dev"
Requires-Dist: nbsphinx==0.9.1; extra == "dev"
Requires-Dist: ipython>=6.4.0; extra == "dev"
Requires-Dist: build>=0.10.0; extra == "dev"
Requires-Dist: matplotlib>=2.2.2; extra == "dev"
Provides-Extra: test
Requires-Dist: pytest>=3.6.2; extra == "test"
Requires-Dist: matplotlib>=2.2.2; extra == "test"
Provides-Extra: lint
Requires-Dist: black; extra == "lint"
Requires-Dist: flake8>=3.5.0; extra == "lint"
Dynamic: license-file
